genword/__init__.py
genword/_utils.py
genword/cli.py
genword-0.1.0.dist-info/LICENSE
genword-0.1.0.dist-info/METADATA
genword-0.1.0.dist-info/WHEEL
genword-0.1.0.dist-info/entry_points.txt
genword-0.1.0.dist-info/RECORD
