Metadata-Version: 2.1
Name: genword
Version: 0.1.0
Summary: Genword é uma ferramenta simples de linha de comando para gerar wordlists.
Author: Henrique Sebastião
Author-email: contato@henriquesebastiao.com
Requires-Python: >=3.11,<4.0
Classifier: Development Status :: 5 - Production/Stable
Classifier: Environment :: Console
Classifier: Natural Language :: English
Classifier: Programming Language :: Python :: 3
Classifier: Programming Language :: Python :: 3.11
Classifier: Programming Language :: Python :: 3.12
Classifier: Topic :: Security
Requires-Dist: rich (>=13.7.0,<14.0.0)
Requires-Dist: typer (>=0.9.0,<0.10.0)
Project-URL: Bug Tracker, https://github.com/henriquesebastiao/genword/issues
Project-URL: Repository, https://github.com/henriquesebastiao/genword
